{"nameMap":"MapNormal_20","tiles":[{"name":"Tile_4","posObject":[{"position":{"x":-2.549999952316284,"y":0.0,"z":-2.549999952316284},"scale":{"x":1.0,"y":1.0,"z":1.0},"rotation":{"x":0.0,"y":180.0,"z":0.0}},{"position":{"x":2.549999952316284,"y":0.0,"z":-2.549999952316284},"scale":{"x":1.0,"y":1.0,"z":1.0},"rotation":{"x":0.0,"y":180.0,"z":0.0}},{"position":{"x":7.649999618530273,"y":0.0,"z":-2.549999952316284},"scale":{"x":1.0,"y":1.0,"z":1.0},"rotation":{"x":0.0,"y":180.0,"z":0.0}},{"position":{"x":12.75,"y":0.0,"z":-2.549999952316284},"scale":{"x":1.0,"y":1.0,"z":1.0},"rotation":{"x":0.0,"y":180.0,"z":0.0}},{"position":{"x":-7.649999618530273,"y":0.0,"z":-2.549999952316284},"scale":{"x":1.0,"y":1.0,"z":1.0},"rotation":{"x":0.0,"y":180.0,"z":0.0}},{"position":{"x":-12.749999046325684,"y":0.0,"z":12.75},"scale":{"x":1.0,"y":1.0,"z":1.0},"rotation":{"x":0.0,"y":270.0,"z":0.0}},{"position":{"x":-12.749999046325684,"y":0.0,"z":7.649999618530273},"scale":{"x":1.0,"y":1.0,"z":1.0},"rotation":{"x":0.0,"y":270.0,"z":0.0}},{"position":{"x":-12.749999046325684,"y":0.0,"z":2.549999952316284},"scale":{"x":1.0,"y":1.0,"z":1.0},"rotation":{"x":0.0,"y":270.0,"z":0.0}},{"position":{"x":-12.749999046325684,"y":0.0,"z":17.849998474121095},"scale":{"x":1.0,"y":1.0,"z":1.0},"rotation":{"x":0.0,"y":270.0,"z":0.0}},{"position":{"x":17.849998474121095,"y":0.0,"z":17.849998474121095},"scale":{"x":1.0,"y":1.0,"z":1.0},"rotation":{"x":0.0,"y":90.0,"z":0.0}},{"position":{"x":17.849998474121095,"y":0.0,"z":12.75},"scale":{"x":1.0,"y":1.0,"z":1.0},"rotation":{"x":0.0,"y":90.0,"z":0.0}},{"position":{"x":17.849998474121095,"y":0.0,"z":7.649999618530273},"scale":{"x":1.0,"y":1.0,"z":1.0},"rotation":{"x":0.0,"y":90.0,"z":0.0}},{"position":{"x":17.849998474121095,"y":0.0,"z":2.549999952316284},"scale":{"x":1.0,"y":1.0,"z":1.0},"rotation":{"x":0.0,"y":90.0,"z":0.0}},{"position":{"x":-12.749999046325684,"y":0.0,"z":22.94999885559082},"scale":{"x":1.0,"y":1.0,"z":1.0},"rotation":{"x":0.0,"y":270.0,"z":0.0}},{"position":{"x":17.849998474121095,"y":0.0,"z":22.94999885559082},"scale":{"x":1.0,"y":1.0,"z":1.0},"rotation":{"x":0.0,"y":90.0,"z":0.0}},{"position":{"x":12.75,"y":0.0,"z":28.049999237060548},"scale":{"x":1.0,"y":1.0,"z":1.0},"rotation":{"x":0.0,"y":0.0,"z":0.0}},{"position":{"x":7.649999618530273,"y":0.0,"z":28.049999237060548},"scale":{"x":1.0,"y":1.0,"z":1.0},"rotation":{"x":0.0,"y":0.0,"z":0.0}},{"position":{"x":2.549999952316284,"y":0.0,"z":28.049999237060548},"scale":{"x":1.0,"y":1.0,"z":1.0},"rotation":{"x":0.0,"y":0.0,"z":0.0}},{"position":{"x":-2.549999952316284,"y":0.0,"z":28.049999237060548},"scale":{"x":1.0,"y":1.0,"z":1.0},"rotation":{"x":0.0,"y":0.0,"z":0.0}},{"position":{"x":-7.649999618530273,"y":0.0,"z":28.049999237060548},"scale":{"x":1.0,"y":1.0,"z":1.0},"rotation":{"x":0.0,"y":0.0,"z":0.0}}]},{"name":"Tile_2","posObject":[{"position":{"x":17.849998474121095,"y":0.0,"z":-2.549999952316284},"scale":{"x":1.0,"y":1.0,"z":1.0},"rotation":{"x":0.0,"y":180.0,"z":0.0}},{"position":{"x":-12.749999046325684,"y":0.0,"z":-2.549999952316284},"scale":{"x":1.0,"y":1.0,"z":1.0},"rotation":{"x":0.0,"y":270.0,"z":0.0}},{"position":{"x":-12.749999046325684,"y":0.0,"z":28.049999237060548},"scale":{"x":1.0,"y":1.0,"z":1.0},"rotation":{"x":0.0,"y":0.0,"z":0.0}},{"position":{"x":17.849998474121095,"y":0.0,"z":28.049999237060548},"scale":{"x":1.0,"y":1.0,"z":1.0},"rotation":{"x":0.0,"y":90.0,"z":0.0}}]},{"name":"Tile_1","posObject":[{"position":{"x":12.75,"y":0.0,"z":12.75},"scale":{"x":1.0,"y":1.0,"z":1.0},"rotation":{"x":0.0,"y":90.0,"z":0.0}},{"position":{"x":12.75,"y":0.0,"z":2.549999952316284},"scale":{"x":1.0,"y":1.0,"z":1.0},"rotation":{"x":0.0,"y":90.0,"z":0.0}},{"position":{"x":-7.649999618530273,"y":0.0,"z":17.849998474121095},"scale":{"x":1.0,"y":1.0,"z":1.0},"rotation":{"x":0.0,"y":0.0,"z":0.0}},{"position":{"x":-2.549999952316284,"y":0.0,"z":22.94999885559082},"scale":{"x":1.0,"y":1.0,"z":1.0},"rotation":{"x":0.0,"y":0.0,"z":0.0}},{"position":{"x":2.549999952316284,"y":0.0,"z":12.75},"scale":{"x":1.0,"y":1.0,"z":1.0},"rotation":{"x":0.0,"y":0.0,"z":0.0}},{"position":{"x":-2.549999952316284,"y":0.0,"z":12.75},"scale":{"x":1.0,"y":1.0,"z":1.0},"rotation":{"x":0.0,"y":0.0,"z":0.0}},{"position":{"x":-2.549999952316284,"y":0.0,"z":17.849998474121095},"scale":{"x":1.0,"y":1.0,"z":1.0},"rotation":{"x":0.0,"y":0.0,"z":0.0}},{"position":{"x":2.549999952316284,"y":0.0,"z":17.849998474121095},"scale":{"x":1.0,"y":1.0,"z":1.0},"rotation":{"x":0.0,"y":0.0,"z":0.0}},{"position":{"x":-7.649999618530273,"y":0.0,"z":22.94999885559082},"scale":{"x":1.0,"y":1.0,"z":1.0},"rotation":{"x":0.0,"y":0.0,"z":0.0}},{"position":{"x":2.549999952316284,"y":0.0,"z":22.94999885559082},"scale":{"x":1.0,"y":1.0,"z":1.0},"rotation":{"x":0.0,"y":0.0,"z":0.0}},{"position":{"x":7.649999618530273,"y":0.0,"z":22.94999885559082},"scale":{"x":1.0,"y":1.0,"z":1.0},"rotation":{"x":0.0,"y":0.0,"z":0.0}},{"position":{"x":12.75,"y":0.0,"z":17.849998474121095},"scale":{"x":1.0,"y":1.0,"z":1.0},"rotation":{"x":0.0,"y":0.0,"z":0.0}},{"position":{"x":12.75,"y":0.0,"z":22.94999885559082},"scale":{"x":1.0,"y":1.0,"z":1.0},"rotation":{"x":0.0,"y":0.0,"z":0.0}},{"position":{"x":7.649999618530273,"y":0.0,"z":17.849998474121095},"scale":{"x":1.0,"y":1.0,"z":1.0},"rotation":{"x":0.0,"y":0.0,"z":0.0}},{"position":{"x":7.649999618530273,"y":0.0,"z":12.75},"scale":{"x":1.0,"y":1.0,"z":1.0},"rotation":{"x":0.0,"y":0.0,"z":0.0}},{"position":{"x":2.549999952316284,"y":0.0,"z":7.649999618530273},"scale":{"x":1.0,"y":1.0,"z":1.0},"rotation":{"x":0.0,"y":0.0,"z":0.0}},{"position":{"x":-7.649999618530273,"y":0.0,"z":12.75},"scale":{"x":1.0,"y":1.0,"z":1.0},"rotation":{"x":0.0,"y":0.0,"z":0.0}},{"position":{"x":-7.649999618530273,"y":0.0,"z":7.649999618530273},"scale":{"x":1.0,"y":1.0,"z":1.0},"rotation":{"x":0.0,"y":0.0,"z":0.0}},{"position":{"x":-7.649999618530273,"y":0.0,"z":2.549999952316284},"scale":{"x":1.0,"y":1.0,"z":1.0},"rotation":{"x":0.0,"y":0.0,"z":0.0}},{"position":{"x":-2.549999952316284,"y":0.0,"z":2.549999952316284},"scale":{"x":1.0,"y":1.0,"z":1.0},"rotation":{"x":0.0,"y":0.0,"z":0.0}},{"position":{"x":-2.549999952316284,"y":0.0,"z":7.649999618530273},"scale":{"x":1.0,"y":1.0,"z":1.0},"rotation":{"x":0.0,"y":0.0,"z":0.0}},{"position":{"x":2.549999952316284,"y":0.0,"z":2.549999952316284},"scale":{"x":1.0,"y":1.0,"z":1.0},"rotation":{"x":0.0,"y":0.0,"z":0.0}},{"position":{"x":7.649999618530273,"y":0.0,"z":2.549999952316284},"scale":{"x":1.0,"y":1.0,"z":1.0},"rotation":{"x":0.0,"y":0.0,"z":0.0}},{"position":{"x":7.649999618530273,"y":0.0,"z":7.649999618530273},"scale":{"x":1.0,"y":1.0,"z":1.0},"rotation":{"x":0.0,"y":0.0,"z":0.0}},{"position":{"x":12.75,"y":0.0,"z":7.649999618530273},"scale":{"x":1.0,"y":1.0,"z":1.0},"rotation":{"x":0.0,"y":0.0,"z":0.0}}]}]}